devtools_binary_text/__init__.py
devtools_binary_text-1.0.1.dist-info/METADATA
devtools_binary_text-1.0.1.dist-info/WHEEL
devtools_binary_text-1.0.1.dist-info/top_level.txt
devtools_binary_text-1.0.1.dist-info/RECORD
