Metadata-Version: 2.1
Name: devtools-binary-text
Version: 1.0.1
Summary: Binary to text converter
Home-page: https://devtools.at/tools/binary-text
Author: DevTools.at
Author-email: hello@devtools.at
Project-URL: Homepage, https://devtools.at/tools/binary-text
Project-URL: Repository, https://github.com/devtools-at/binary-text
Classifier: Development Status :: 4 - Beta
Classifier: Intended Audience :: Developers
Classifier: License :: OSI Approved :: MIT License
Classifier: Programming Language :: Python :: 3
Requires-Python: >=3.8
